pyjpboatrace/__init__.py
pyjpboatrace/certification.py
pyjpboatrace/const.py
pyjpboatrace/drivers.py
pyjpboatrace/exceptions.py
pyjpboatrace/pyjpboatrace.py
pyjpboatrace/user_information.py
pyjpboatrace/validator.py
pyjpboatrace/operator/__init__.py
pyjpboatrace/operator/base.py
pyjpboatrace/operator/better.py
pyjpboatrace/operator/betting_limit_checker.py
pyjpboatrace/operator/depositor.py
pyjpboatrace/operator/static.py
pyjpboatrace/operator/withdrawer.py
pyjpboatrace/scraper/__init__.py
pyjpboatrace/scraper/base.py
pyjpboatrace/scraper/exacta_quinella_odds_scraper.py
pyjpboatrace/scraper/just_before_info_scraper.py
pyjpboatrace/scraper/quinellaplace_odds_scraper.py
pyjpboatrace/scraper/race_info_scraper.py
pyjpboatrace/scraper/races_scraper.py
pyjpboatrace/scraper/result_scraper.py
pyjpboatrace/scraper/stadiums_scraper.py
pyjpboatrace/scraper/trifecta_odds_scraper.py
pyjpboatrace/scraper/trio_odds_scraper.py
pyjpboatrace/scraper/win_placeshow_odds_scraper.py
pyjpboatrace/scraper/_parser/__init__.py
pyjpboatrace/scraper/_parser/parse_html_beforeinfo.py
pyjpboatrace/scraper/_parser/parse_html_index.py
pyjpboatrace/scraper/_parser/parse_html_odds2tf.py
pyjpboatrace/scraper/_parser/parse_html_odds3f.py
pyjpboatrace/scraper/_parser/parse_html_odds3t.py
pyjpboatrace/scraper/_parser/parse_html_oddsk.py
pyjpboatrace/scraper/_parser/parse_html_oddstf.py
pyjpboatrace/scraper/_parser/parse_html_raceindex.py
pyjpboatrace/scraper/_parser/parse_html_racelist.py
pyjpboatrace/scraper/_parser/parse_html_raceresult.py
pyjpboatrace/scraper/_parser/scrape_odds_update_time.py
pyjpboatrace/utils/__init__.py
pyjpboatrace/utils/str2num.py
pyjpboatrace-0.5.0.dist-info/licenses/LICENSE
pyjpboatrace-0.5.0.dist-info/METADATA
pyjpboatrace-0.5.0.dist-info/WHEEL
pyjpboatrace-0.5.0.dist-info/top_level.txt
pyjpboatrace-0.5.0.dist-info/RECORD
