Metadata-Version: 2.4
Name: pyjpboatrace
Version: 0.5.0
Summary: PyJPBoatrace: Python-based Japanese boatrace tools
Author-email: hmasdev <hmasuidev1com@gmail.com>
License: MIT License
Project-URL: Repository, https://github.com/hmasdev/pyjpboatrace
Keywords: kyotei,boatrace,data analysis
Classifier: Development Status :: 2 - Pre-Alpha
Classifier: License :: OSI Approved :: MIT License
Classifier: Programming Language :: Python :: 3.9
Classifier: Programming Language :: Python :: 3.10
Classifier: Programming Language :: Python :: 3.11
Classifier: Programming Language :: Python :: 3.12
Classifier: Programming Language :: Python :: 3.13
Requires-Python: >=3.9
License-File: LICENSE
Requires-Dist: beautifulsoup4>=4.11.1
Requires-Dist: requests>=2.28.1
Requires-Dist: selenium>=4.6.0
Provides-Extra: dev
Requires-Dist: autopep8>=2.3.1; extra == "dev"
Requires-Dist: jinja2>=3.1.5; extra == "dev"
Requires-Dist: mypy>=1.14.0; extra == "dev"
Requires-Dist: pytest>=8.3.4; extra == "dev"
Requires-Dist: pytest-cov>=6.0.0; extra == "dev"
Requires-Dist: pytz>=2024.2; extra == "dev"
Requires-Dist: ruff>=0.11.6; extra == "dev"
Requires-Dist: twine>=6.0.1; extra == "dev"
Requires-Dist: types-beautifulsoup4; extra == "dev"
Requires-Dist: types-pytz>=2024.2.0.20241221; extra == "dev"
Requires-Dist: types-requests; extra == "dev"
Dynamic: license-file
